{
  "changes" : [ {
    "event_info" : {
      "date" : "12/08/2025 16:47:41",
      "sequence" : 500058,
      "date_format" : "dd/mm/rrrr hh24:mi:ss",
      "dml_operation" : "INSERT",
      "table_name" : "TABELA_ATRIBUTO",
      "tag_name" : "CMDK",
      "tasy_user" : "tpsantos",
      "guid" : "a5673d11-a5d7-433b-8782-658d5938d463"
    },
    "server_info" : {
      "charset" : "AMERICAN_AMERICA.AL32UTF8",
      "database_version" : "19.0",
      "instance_name" : "phcdb1"
    },
    "session_info" : {
      "machine" : "0465e5611e89",
      "os_user" : "root",
      "tasy_user" : "tpsantos"
    },
    "primary_key_values" : [ {
      "column_name" : "NM_TABELA",
      "data_type" : "VARCHAR2",
      "new_value" : "VVRE_TPS_AUT_CONV_HIST",
      "old_value" : null
    }, {
      "column_name" : "NM_ATRIBUTO",
      "data_type" : "VARCHAR2",
      "new_value" : "NR_SEQUENCIA",
      "old_value" : null
    } ],
    "column_values" : [ {
      "column_name" : "NR_SEQUENCIA_CRIACAO",
      "data_type" : "NUMBER",
      "new_value" : 10,
      "old_value" : null
    }, {
      "column_name" : "IE_OBRIGATORIO",
      "data_type" : "VARCHAR2",
      "new_value" : "N",
      "old_value" : null
    }, {
      "column_name" : "NM_USUARIO",
      "data_type" : "VARCHAR2",
      "new_value" : "tpsantos",
      "old_value" : null
    }, {
      "column_name" : "QT_DECIMAIS",
      "data_type" : "NUMBER",
      "new_value" : 0,
      "old_value" : null
    }, {
      "column_name" : "IE_CRIAR_ALTERAR",
      "data_type" : "VARCHAR2",
      "new_value" : "M",
      "old_value" : null
    }, {
      "column_name" : "IE_SITUACAO",
      "data_type" : "VARCHAR2",
      "new_value" : "A",
      "old_value" : null
    }, {
      "column_name" : "NM_ATRIBUTO",
      "data_type" : "VARCHAR2",
      "new_value" : "NR_SEQUENCIA",
      "old_value" : null
    }, {
      "column_name" : "IE_LOG_EXCLUSAO",
      "data_type" : "VARCHAR2",
      "new_value" : "N",
      "old_value" : null
    }, {
      "column_name" : "QT_TAMANHO",
      "data_type" : "NUMBER",
      "new_value" : 10,
      "old_value" : null
    }, {
      "column_name" : "NM_TABELA",
      "data_type" : "VARCHAR2",
      "new_value" : "VVRE_TPS_AUT_CONV_HIST",
      "old_value" : null
    }, {
      "column_name" : "DT_CRIACAO",
      "data_type" : "DATE",
      "new_value" : "12/08/2025 16:40:46",
      "old_value" : null
    }, {
      "column_name" : "IE_CRIAR_DESCRICAO",
      "data_type" : "VARCHAR2",
      "new_value" : "N",
      "old_value" : null
    }, {
      "column_name" : "NM_ATRIBUTO_PAI",
      "data_type" : "VARCHAR2",
      "new_value" : "",
      "old_value" : null
    }, {
      "column_name" : "IE_READONLY",
      "data_type" : "VARCHAR2",
      "new_value" : "N",
      "old_value" : null
    }, {
      "column_name" : "IE_TABSTOP",
      "data_type" : "VARCHAR2",
      "new_value" : "S",
      "old_value" : null
    }, {
      "column_name" : "DT_ATUALIZACAO",
      "data_type" : "DATE",
      "new_value" : "12/08/2025 16:40:46",
      "old_value" : null
    }, {
      "column_name" : "IE_TIPO_ATRIBUTO",
      "data_type" : "VARCHAR2",
      "new_value" : "NUMBER",
      "old_value" : null
    }, {
      "column_name" : "IE_CONVERTE_NEGATIVO",
      "data_type" : "VARCHAR2",
      "new_value" : "N",
      "old_value" : null
    }, {
      "column_name" : "IE_LOG_UPDATE",
      "data_type" : "VARCHAR2",
      "new_value" : "N",
      "old_value" : null
    }, {
      "column_name" : "IE_ATUALIZAR_VERSAO",
      "data_type" : "VARCHAR2",
      "new_value" : "N",
      "old_value" : null
    }, {
      "column_name" : "IE_STATUS",
      "data_type" : "VARCHAR2",
      "new_value" : "N",
      "old_value" : null
    }, {
      "column_name" : "IE_CRIAR_DESC_FK",
      "data_type" : "VARCHAR2",
      "new_value" : "S",
      "old_value" : null
    }, {
      "column_name" : "IE_UNIDADE_MEDIDA",
      "data_type" : "VARCHAR2",
      "new_value" : "S",
      "old_value" : null
    }, {
      "column_name" : "IE_REGRA_UNID_MEDIDA",
      "data_type" : "VARCHAR2",
      "new_value" : "N",
      "old_value" : null
    }, {
      "column_name" : "IE_DBL_CLICK_READONLY",
      "data_type" : "VARCHAR2",
      "new_value" : "N",
      "old_value" : null
    }, {
      "column_name" : "IE_DEFAULT_BANCO",
      "data_type" : "VARCHAR2",
      "new_value" : "N",
      "old_value" : null
    }, {
      "column_name" : "CD_EXP_DESC",
      "data_type" : "NUMBER",
      "new_value" : 488948,
      "old_value" : null
    }, {
      "column_name" : "IE_INFORMACAO_SENSIVEL",
      "data_type" : "VARCHAR2",
      "new_value" : "N",
      "old_value" : null
    } ]
  }, {
    "event_info" : {
      "date" : "12/08/2025 16:47:41",
      "sequence" : 500059,
      "date_format" : "dd/mm/rrrr hh24:mi:ss",
      "dml_operation" : "INSERT",
      "table_name" : "TABELA_ATRIBUTO",
      "tag_name" : "CMDK",
      "tasy_user" : "tpsantos",
      "guid" : "fd585eb9-8c32-46ab-b7d0-d4176ddf1a47"
    },
    "server_info" : {
      "charset" : "AMERICAN_AMERICA.AL32UTF8",
      "database_version" : "19.0",
      "instance_name" : "phcdb1"
    },
    "session_info" : {
      "machine" : "0465e5611e89",
      "os_user" : "root",
      "tasy_user" : "tpsantos"
    },
    "primary_key_values" : [ {
      "column_name" : "NM_TABELA",
      "data_type" : "VARCHAR2",
      "new_value" : "VVRE_TPS_AUT_CONV_HIST",
      "old_value" : null
    }, {
      "column_name" : "NM_ATRIBUTO",
      "data_type" : "VARCHAR2",
      "new_value" : "NR_SEQ_AUTORIZACAO",
      "old_value" : null
    } ],
    "column_values" : [ {
      "column_name" : "NR_SEQUENCIA_CRIACAO",
      "data_type" : "NUMBER",
      "new_value" : 20,
      "old_value" : null
    }, {
      "column_name" : "IE_OBRIGATORIO",
      "data_type" : "VARCHAR2",
      "new_value" : "N",
      "old_value" : null
    }, {
      "column_name" : "NM_USUARIO",
      "data_type" : "VARCHAR2",
      "new_value" : "tpsantos",
      "old_value" : null
    }, {
      "column_name" : "QT_DECIMAIS",
      "data_type" : "NUMBER",
      "new_value" : 0,
      "old_value" : null
    }, {
      "column_name" : "IE_CRIAR_ALTERAR",
      "data_type" : "VARCHAR2",
      "new_value" : "M",
      "old_value" : null
    }, {
      "column_name" : "IE_SITUACAO",
      "data_type" : "VARCHAR2",
      "new_value" : "A",
      "old_value" : null
    }, {
      "column_name" : "NM_ATRIBUTO",
      "data_type" : "VARCHAR2",
      "new_value" : "NR_SEQ_AUTORIZACAO",
      "old_value" : null
    }, {
      "column_name" : "IE_LOG_EXCLUSAO",
      "data_type" : "VARCHAR2",
      "new_value" : "N",
      "old_value" : null
    }, {
      "column_name" : "QT_TAMANHO",
      "data_type" : "NUMBER",
      "new_value" : 10,
      "old_value" : null
    }, {
      "column_name" : "NM_TABELA",
      "data_type" : "VARCHAR2",
      "new_value" : "VVRE_TPS_AUT_CONV_HIST",
      "old_value" : null
    }, {
      "column_name" : "DT_CRIACAO",
      "data_type" : "DATE",
      "new_value" : "12/08/2025 16:41:16",
      "old_value" : null
    }, {
      "column_name" : "IE_CRIAR_DESCRICAO",
      "data_type" : "VARCHAR2",
      "new_value" : "N",
      "old_value" : null
    }, {
      "column_name" : "NM_ATRIBUTO_PAI",
      "data_type" : "VARCHAR2",
      "new_value" : "",
      "old_value" : null
    }, {
      "column_name" : "IE_READONLY",
      "data_type" : "VARCHAR2",
      "new_value" : "N",
      "old_value" : null
    }, {
      "column_name" : "IE_TABSTOP",
      "data_type" : "VARCHAR2",
      "new_value" : "S",
      "old_value" : null
    }, {
      "column_name" : "DT_ATUALIZACAO",
      "data_type" : "DATE",
      "new_value" : "12/08/2025 16:41:16",
      "old_value" : null
    }, {
      "column_name" : "IE_TIPO_ATRIBUTO",
      "data_type" : "VARCHAR2",
      "new_value" : "NUMBER",
      "old_value" : null
    }, {
      "column_name" : "IE_CONVERTE_NEGATIVO",
      "data_type" : "VARCHAR2",
      "new_value" : "N",
      "old_value" : null
    }, {
      "column_name" : "IE_LOG_UPDATE",
      "data_type" : "VARCHAR2",
      "new_value" : "N",
      "old_value" : null
    }, {
      "column_name" : "IE_ATUALIZAR_VERSAO",
      "data_type" : "VARCHAR2",
      "new_value" : "N",
      "old_value" : null
    }, {
      "column_name" : "IE_STATUS",
      "data_type" : "VARCHAR2",
      "new_value" : "N",
      "old_value" : null
    }, {
      "column_name" : "IE_CRIAR_DESC_FK",
      "data_type" : "VARCHAR2",
      "new_value" : "S",
      "old_value" : null
    }, {
      "column_name" : "IE_UNIDADE_MEDIDA",
      "data_type" : "VARCHAR2",
      "new_value" : "S",
      "old_value" : null
    }, {
      "column_name" : "IE_REGRA_UNID_MEDIDA",
      "data_type" : "VARCHAR2",
      "new_value" : "N",
      "old_value" : null
    }, {
      "column_name" : "IE_DBL_CLICK_READONLY",
      "data_type" : "VARCHAR2",
      "new_value" : "N",
      "old_value" : null
    }, {
      "column_name" : "IE_DEFAULT_BANCO",
      "data_type" : "VARCHAR2",
      "new_value" : "N",
      "old_value" : null
    }, {
      "column_name" : "CD_EXP_DESC",
      "data_type" : "NUMBER",
      "new_value" : 306292,
      "old_value" : null
    }, {
      "column_name" : "IE_INFORMACAO_SENSIVEL",
      "data_type" : "VARCHAR2",
      "new_value" : "N",
      "old_value" : null
    } ]
  }, {
    "event_info" : {
      "date" : "12/08/2025 16:47:41",
      "sequence" : 500060,
      "date_format" : "dd/mm/rrrr hh24:mi:ss",
      "dml_operation" : "INSERT",
      "table_name" : "TABELA_ATRIBUTO",
      "tag_name" : "CMDK",
      "tasy_user" : "tpsantos",
      "guid" : "6377b2ab-d3ec-46cf-ae7c-dc94277cea94"
    },
    "server_info" : {
      "charset" : "AMERICAN_AMERICA.AL32UTF8",
      "database_version" : "19.0",
      "instance_name" : "phcdb1"
    },
    "session_info" : {
      "machine" : "0465e5611e89",
      "os_user" : "root",
      "tasy_user" : "tpsantos"
    },
    "primary_key_values" : [ {
      "column_name" : "NM_TABELA",
      "data_type" : "VARCHAR2",
      "new_value" : "VVRE_TPS_AUT_CONV_HIST",
      "old_value" : null
    }, {
      "column_name" : "NM_ATRIBUTO",
      "data_type" : "VARCHAR2",
      "new_value" : "IE_TIPO",
      "old_value" : null
    } ],
    "column_values" : [ {
      "column_name" : "NR_SEQUENCIA_CRIACAO",
      "data_type" : "NUMBER",
      "new_value" : 30,
      "old_value" : null
    }, {
      "column_name" : "IE_OBRIGATORIO",
      "data_type" : "VARCHAR2",
      "new_value" : "N",
      "old_value" : null
    }, {
      "column_name" : "NM_USUARIO",
      "data_type" : "VARCHAR2",
      "new_value" : "tpsantos",
      "old_value" : null
    }, {
      "column_name" : "IE_CRIAR_ALTERAR",
      "data_type" : "VARCHAR2",
      "new_value" : "M",
      "old_value" : null
    }, {
      "column_name" : "IE_SITUACAO",
      "data_type" : "VARCHAR2",
      "new_value" : "A",
      "old_value" : null
    }, {
      "column_name" : "NM_ATRIBUTO",
      "data_type" : "VARCHAR2",
      "new_value" : "IE_TIPO",
      "old_value" : null
    }, {
      "column_name" : "IE_LOG_EXCLUSAO",
      "data_type" : "VARCHAR2",
      "new_value" : "N",
      "old_value" : null
    }, {
      "column_name" : "QT_TAMANHO",
      "data_type" : "NUMBER",
      "new_value" : 1,
      "old_value" : null
    }, {
      "column_name" : "NM_TABELA",
      "data_type" : "VARCHAR2",
      "new_value" : "VVRE_TPS_AUT_CONV_HIST",
      "old_value" : null
    }, {
      "column_name" : "DT_CRIACAO",
      "data_type" : "DATE",
      "new_value" : "12/08/2025 16:43:17",
      "old_value" : null
    }, {
      "column_name" : "IE_CRIAR_DESCRICAO",
      "data_type" : "VARCHAR2",
      "new_value" : "N",
      "old_value" : null
    }, {
      "column_name" : "NM_ATRIBUTO_PAI",
      "data_type" : "VARCHAR2",
      "new_value" : "",
      "old_value" : null
    }, {
      "column_name" : "IE_READONLY",
      "data_type" : "VARCHAR2",
      "new_value" : "N",
      "old_value" : null
    }, {
      "column_name" : "IE_TABSTOP",
      "data_type" : "VARCHAR2",
      "new_value" : "S",
      "old_value" : null
    }, {
      "column_name" : "DT_ATUALIZACAO",
      "data_type" : "DATE",
      "new_value" : "12/08/2025 16:43:17",
      "old_value" : null
    }, {
      "column_name" : "IE_TIPO_ATRIBUTO",
      "data_type" : "VARCHAR2",
      "new_value" : "VARCHAR2",
      "old_value" : null
    }, {
      "column_name" : "IE_CONVERTE_NEGATIVO",
      "data_type" : "VARCHAR2",
      "new_value" : "N",
      "old_value" : null
    }, {
      "column_name" : "IE_LOG_UPDATE",
      "data_type" : "VARCHAR2",
      "new_value" : "N",
      "old_value" : null
    }, {
      "column_name" : "IE_ATUALIZAR_VERSAO",
      "data_type" : "VARCHAR2",
      "new_value" : "N",
      "old_value" : null
    }, {
      "column_name" : "IE_STATUS",
      "data_type" : "VARCHAR2",
      "new_value" : "N",
      "old_value" : null
    }, {
      "column_name" : "IE_CRIAR_DESC_FK",
      "data_type" : "VARCHAR2",
      "new_value" : "S",
      "old_value" : null
    }, {
      "column_name" : "IE_UNIDADE_MEDIDA",
      "data_type" : "VARCHAR2",
      "new_value" : "S",
      "old_value" : null
    }, {
      "column_name" : "IE_REGRA_UNID_MEDIDA",
      "data_type" : "VARCHAR2",
      "new_value" : "N",
      "old_value" : null
    }, {
      "column_name" : "IE_DBL_CLICK_READONLY",
      "data_type" : "VARCHAR2",
      "new_value" : "N",
      "old_value" : null
    }, {
      "column_name" : "IE_DEFAULT_BANCO",
      "data_type" : "VARCHAR2",
      "new_value" : "N",
      "old_value" : null
    }, {
      "column_name" : "CD_EXP_DESC",
      "data_type" : "NUMBER",
      "new_value" : 658799,
      "old_value" : null
    }, {
      "column_name" : "IE_INFORMACAO_SENSIVEL",
      "data_type" : "VARCHAR2",
      "new_value" : "N",
      "old_value" : null
    } ]
  }, {
    "event_info" : {
      "date" : "12/08/2025 16:47:41",
      "sequence" : 500061,
      "date_format" : "dd/mm/rrrr hh24:mi:ss",
      "dml_operation" : "INSERT",
      "table_name" : "TABELA_ATRIBUTO",
      "tag_name" : "CMDK",
      "tasy_user" : "tpsantos",
      "guid" : "d47f7f2e-9639-4150-ae96-843427e0847b"
    },
    "server_info" : {
      "charset" : "AMERICAN_AMERICA.AL32UTF8",
      "database_version" : "19.0",
      "instance_name" : "phcdb1"
    },
    "session_info" : {
      "machine" : "0465e5611e89",
      "os_user" : "root",
      "tasy_user" : "tpsantos"
    },
    "primary_key_values" : [ {
      "column_name" : "NM_TABELA",
      "data_type" : "VARCHAR2",
      "new_value" : "VVRE_TPS_AUT_CONV_HIST",
      "old_value" : null
    }, {
      "column_name" : "NM_ATRIBUTO",
      "data_type" : "VARCHAR2",
      "new_value" : "DS_HISTORICO",
      "old_value" : null
    } ],
    "column_values" : [ {
      "column_name" : "NR_SEQUENCIA_CRIACAO",
      "data_type" : "NUMBER",
      "new_value" : 40,
      "old_value" : null
    }, {
      "column_name" : "IE_OBRIGATORIO",
      "data_type" : "VARCHAR2",
      "new_value" : "N",
      "old_value" : null
    }, {
      "column_name" : "NM_USUARIO",
      "data_type" : "VARCHAR2",
      "new_value" : "tpsantos",
      "old_value" : null
    }, {
      "column_name" : "IE_CRIAR_ALTERAR",
      "data_type" : "VARCHAR2",
      "new_value" : "M",
      "old_value" : null
    }, {
      "column_name" : "IE_SITUACAO",
      "data_type" : "VARCHAR2",
      "new_value" : "A",
      "old_value" : null
    }, {
      "column_name" : "NM_ATRIBUTO",
      "data_type" : "VARCHAR2",
      "new_value" : "DS_HISTORICO",
      "old_value" : null
    }, {
      "column_name" : "IE_LOG_EXCLUSAO",
      "data_type" : "VARCHAR2",
      "new_value" : "N",
      "old_value" : null
    }, {
      "column_name" : "QT_TAMANHO",
      "data_type" : "NUMBER",
      "new_value" : 255,
      "old_value" : null
    }, {
      "column_name" : "NM_TABELA",
      "data_type" : "VARCHAR2",
      "new_value" : "VVRE_TPS_AUT_CONV_HIST",
      "old_value" : null
    }, {
      "column_name" : "DT_CRIACAO",
      "data_type" : "DATE",
      "new_value" : "12/08/2025 16:43:53",
      "old_value" : null
    }, {
      "column_name" : "IE_CRIAR_DESCRICAO",
      "data_type" : "VARCHAR2",
      "new_value" : "N",
      "old_value" : null
    }, {
      "column_name" : "NM_ATRIBUTO_PAI",
      "data_type" : "VARCHAR2",
      "new_value" : "",
      "old_value" : null
    }, {
      "column_name" : "IE_READONLY",
      "data_type" : "VARCHAR2",
      "new_value" : "N",
      "old_value" : null
    }, {
      "column_name" : "IE_TABSTOP",
      "data_type" : "VARCHAR2",
      "new_value" : "S",
      "old_value" : null
    }, {
      "column_name" : "DT_ATUALIZACAO",
      "data_type" : "DATE",
      "new_value" : "12/08/2025 16:43:53",
      "old_value" : null
    }, {
      "column_name" : "IE_TIPO_ATRIBUTO",
      "data_type" : "VARCHAR2",
      "new_value" : "VARCHAR2",
      "old_value" : null
    }, {
      "column_name" : "IE_CONVERTE_NEGATIVO",
      "data_type" : "VARCHAR2",
      "new_value" : "N",
      "old_value" : null
    }, {
      "column_name" : "IE_LOG_UPDATE",
      "data_type" : "VARCHAR2",
      "new_value" : "N",
      "old_value" : null
    }, {
      "column_name" : "IE_ATUALIZAR_VERSAO",
      "data_type" : "VARCHAR2",
      "new_value" : "N",
      "old_value" : null
    }, {
      "column_name" : "IE_STATUS",
      "data_type" : "VARCHAR2",
      "new_value" : "N",
      "old_value" : null
    }, {
      "column_name" : "IE_CRIAR_DESC_FK",
      "data_type" : "VARCHAR2",
      "new_value" : "S",
      "old_value" : null
    }, {
      "column_name" : "IE_UNIDADE_MEDIDA",
      "data_type" : "VARCHAR2",
      "new_value" : "S",
      "old_value" : null
    }, {
      "column_name" : "IE_REGRA_UNID_MEDIDA",
      "data_type" : "VARCHAR2",
      "new_value" : "N",
      "old_value" : null
    }, {
      "column_name" : "IE_DBL_CLICK_READONLY",
      "data_type" : "VARCHAR2",
      "new_value" : "N",
      "old_value" : null
    }, {
      "column_name" : "IE_DEFAULT_BANCO",
      "data_type" : "VARCHAR2",
      "new_value" : "N",
      "old_value" : null
    }, {
      "column_name" : "CD_EXP_DESC",
      "data_type" : "NUMBER",
      "new_value" : 825079,
      "old_value" : null
    }, {
      "column_name" : "IE_INFORMACAO_SENSIVEL",
      "data_type" : "VARCHAR2",
      "new_value" : "N",
      "old_value" : null
    } ]
  }, {
    "event_info" : {
      "date" : "12/08/2025 16:47:41",
      "sequence" : 500062,
      "date_format" : "dd/mm/rrrr hh24:mi:ss",
      "dml_operation" : "DELETE",
      "table_name" : "TIPO_LOCALIZAR_ATRIBUTO",
      "tag_name" : "CMDK",
      "tasy_user" : "tpsantos",
      "guid" : "265f093e-6900-483d-a751-7972cac9ee11"
    },
    "server_info" : {
      "charset" : "AMERICAN_AMERICA.AL32UTF8",
      "database_version" : "19.0",
      "instance_name" : "phcdb1"
    },
    "session_info" : {
      "machine" : "0465e5611e89",
      "os_user" : "root",
      "tasy_user" : "tpsantos"
    },
    "primary_key_values" : [ {
      "column_name" : "NR_SEQUENCIA",
      "data_type" : "NUMBER",
      "new_value" : null,
      "old_value" : 38597
    } ],
    "column_values" : [ {
      "column_name" : "NR_SEQUENCIA",
      "data_type" : "NUMBER",
      "new_value" : null,
      "old_value" : 38597
    }, {
      "column_name" : "DT_ATUALIZACAO",
      "data_type" : "DATE",
      "new_value" : null,
      "old_value" : "12/08/2025 14:12:56"
    }, {
      "column_name" : "NM_USUARIO",
      "data_type" : "VARCHAR2",
      "new_value" : null,
      "old_value" : "tpsantos"
    }, {
      "column_name" : "NR_SEQ_TIPO_LOCALIZAR",
      "data_type" : "NUMBER",
      "new_value" : null,
      "old_value" : 23145
    }, {
      "column_name" : "QT_ALTURA",
      "data_type" : "NUMBER",
      "new_value" : null,
      "old_value" : "21"
    }, {
      "column_name" : "NM_ATRIBUTO",
      "data_type" : "VARCHAR2",
      "new_value" : null,
      "old_value" : "CD_CONVENIO"
    }, {
      "column_name" : "IE_GRID",
      "data_type" : "VARCHAR2",
      "new_value" : null,
      "old_value" : "N"
    }, {
      "column_name" : "IE_TIPO_SELECAO",
      "data_type" : "VARCHAR2",
      "new_value" : null,
      "old_value" : "E"
    }, {
      "column_name" : "IE_RESULTADO",
      "data_type" : "VARCHAR2",
      "new_value" : null,
      "old_value" : "N"
    }, {
      "column_name" : "DS_ITEM",
      "data_type" : "VARCHAR2",
      "new_value" : null,
      "old_value" : "Conv\u00eanio"
    }, {
      "column_name" : "NR_SEQ_APRESENT",
      "data_type" : "NUMBER",
      "new_value" : null,
      "old_value" : 10
    }, {
      "column_name" : "IE_TIPO_ATRIBUTO",
      "data_type" : "VARCHAR2",
      "new_value" : null,
      "old_value" : "NUMBER"
    }, {
      "column_name" : "IE_FOCUS",
      "data_type" : "VARCHAR2",
      "new_value" : null,
      "old_value" : "N"
    }, {
      "column_name" : "QT_DESLOCAMENTO",
      "data_type" : "NUMBER",
      "new_value" : null,
      "old_value" : "0"
    }, {
      "column_name" : "NR_COLUNAS",
      "data_type" : "NUMBER",
      "new_value" : null,
      "old_value" : "0"
    }, {
      "column_name" : "IE_IGNORAR_ACENTUACAO",
      "data_type" : "VARCHAR2",
      "new_value" : null,
      "old_value" : "N"
    }, {
      "column_name" : "IE_OCULTAR_RESTRICAO",
      "data_type" : "VARCHAR2",
      "new_value" : null,
      "old_value" : "N"
    }, {
      "column_name" : "IE_TIPO_RESTRICAO",
      "data_type" : "NUMBER",
      "new_value" : null,
      "old_value" : 1
    }, {
      "column_name" : "IE_DESC_RESULT",
      "data_type" : "VARCHAR2",
      "new_value" : null,
      "old_value" : "N"
    }, {
      "column_name" : "IE_UTILIZA_TARJA_MAGNETICA",
      "data_type" : "VARCHAR2",
      "new_value" : null,
      "old_value" : "N"
    }, {
      "column_name" : "CD_EXP_ITEM",
      "data_type" : "NUMBER",
      "new_value" : null,
      "old_value" : 285268
    }, {
      "column_name" : "NM_USUARIO_NREC",
      "data_type" : "VARCHAR2",
      "new_value" : null,
      "old_value" : "tpsantos"
    }, {
      "column_name" : "DT_ATUALIZACAO_NREC",
      "data_type" : "DATE",
      "new_value" : null,
      "old_value" : "12/08/2025 14:13:58"
    }, {
      "column_name" : "IE_INTERVALO_DATA",
      "data_type" : "VARCHAR2",
      "new_value" : null,
      "old_value" : "N"
    } ]
  }, {
    "event_info" : {
      "date" : "12/08/2025 16:47:41",
      "sequence" : 500063,
      "date_format" : "dd/mm/rrrr hh24:mi:ss",
      "dml_operation" : "DELETE",
      "table_name" : "TIPO_LOCALIZAR_ATRIBUTO",
      "tag_name" : "CMDK",
      "tasy_user" : "tpsantos",
      "guid" : "80c511e6-24d7-4d5e-8a20-cd381378a2dd"
    },
    "server_info" : {
      "charset" : "AMERICAN_AMERICA.AL32UTF8",
      "database_version" : "19.0",
      "instance_name" : "phcdb1"
    },
    "session_info" : {
      "machine" : "0465e5611e89",
      "os_user" : "root",
      "tasy_user" : "tpsantos"
    },
    "primary_key_values" : [ {
      "column_name" : "NR_SEQUENCIA",
      "data_type" : "NUMBER",
      "new_value" : null,
      "old_value" : 38599
    } ],
    "column_values" : [ {
      "column_name" : "NR_SEQUENCIA",
      "data_type" : "NUMBER",
      "new_value" : null,
      "old_value" : 38599
    }, {
      "column_name" : "DT_ATUALIZACAO",
      "data_type" : "DATE",
      "new_value" : null,
      "old_value" : "12/08/2025 14:15:31"
    }, {
      "column_name" : "NM_USUARIO",
      "data_type" : "VARCHAR2",
      "new_value" : null,
      "old_value" : "tpsantos"
    }, {
      "column_name" : "NR_SEQ_TIPO_LOCALIZAR",
      "data_type" : "NUMBER",
      "new_value" : null,
      "old_value" : 23145
    }, {
      "column_name" : "QT_ALTURA",
      "data_type" : "NUMBER",
      "new_value" : null,
      "old_value" : "21"
    }, {
      "column_name" : "NM_ATRIBUTO",
      "data_type" : "VARCHAR2",
      "new_value" : null,
      "old_value" : "DS_CONVENIO"
    }, {
      "column_name" : "IE_GRID",
      "data_type" : "VARCHAR2",
      "new_value" : null,
      "old_value" : "S"
    }, {
      "column_name" : "IE_TIPO_SELECAO",
      "data_type" : "VARCHAR2",
      "new_value" : null,
      "old_value" : "E"
    }, {
      "column_name" : "IE_RESULTADO",
      "data_type" : "VARCHAR2",
      "new_value" : null,
      "old_value" : "N"
    }, {
      "column_name" : "DS_ITEM",
      "data_type" : "VARCHAR2",
      "new_value" : null,
      "old_value" : "Conv\u00eanio"
    }, {
      "column_name" : "NR_SEQ_APRESENT",
      "data_type" : "NUMBER",
      "new_value" : null,
      "old_value" : 10
    }, {
      "column_name" : "QT_TAM_GRID",
      "data_type" : "NUMBER",
      "new_value" : null,
      "old_value" : 12
    }, {
      "column_name" : "NR_SEQ_GRID",
      "data_type" : "NUMBER",
      "new_value" : null,
      "old_value" : 10
    }, {
      "column_name" : "IE_TIPO_ATRIBUTO",
      "data_type" : "VARCHAR2",
      "new_value" : null,
      "old_value" : "VARCHAR2"
    }, {
      "column_name" : "IE_FOCUS",
      "data_type" : "VARCHAR2",
      "new_value" : null,
      "old_value" : "N"
    }, {
      "column_name" : "QT_DESLOCAMENTO",
      "data_type" : "NUMBER",
      "new_value" : null,
      "old_value" : "0"
    }, {
      "column_name" : "NR_COLUNAS",
      "data_type" : "NUMBER",
      "new_value" : null,
      "old_value" : "0"
    }, {
      "column_name" : "IE_IGNORAR_ACENTUACAO",
      "data_type" : "VARCHAR2",
      "new_value" : null,
      "old_value" : "N"
    }, {
      "column_name" : "IE_OCULTAR_RESTRICAO",
      "data_type" : "VARCHAR2",
      "new_value" : null,
      "old_value" : "N"
    }, {
      "column_name" : "QT_TAM_ATRIB_DESC",
      "data_type" : "NUMBER",
      "new_value" : null,
      "old_value" : 12
    }, {
      "column_name" : "IE_TIPO_RESTRICAO",
      "data_type" : "NUMBER",
      "new_value" : null,
      "old_value" : 3
    }, {
      "column_name" : "IE_DESC_RESULT",
      "data_type" : "VARCHAR2",
      "new_value" : null,
      "old_value" : "S"
    }, {
      "column_name" : "IE_UTILIZA_TARJA_MAGNETICA",
      "data_type" : "VARCHAR2",
      "new_value" : null,
      "old_value" : "N"
    }, {
      "column_name" : "QT_TAM_COLUNA_GRID",
      "data_type" : "NUMBER",
      "new_value" : null,
      "old_value" : 500
    }, {
      "column_name" : "CD_EXP_ITEM",
      "data_type" : "NUMBER",
      "new_value" : null,
      "old_value" : 286186
    }, {
      "column_name" : "NM_USUARIO_NREC",
      "data_type" : "VARCHAR2",
      "new_value" : null,
      "old_value" : "tpsantos"
    }, {
      "column_name" : "DT_ATUALIZACAO_NREC",
      "data_type" : "DATE",
      "new_value" : null,
      "old_value" : "12/08/2025 14:47:21"
    }, {
      "column_name" : "IE_INTERVALO_DATA",
      "data_type" : "VARCHAR2",
      "new_value" : null,
      "old_value" : "N"
    } ]
  } ]
}